LICENSE
MANIFEST.in
README.md
setup.py
chiasm_shell/VERSION
chiasm_shell/__init__.py
chiasm_shell/assembler.py
chiasm_shell/backend.py
chiasm_shell/chiasm_shell.py
chiasm_shell/config.py
chiasm_shell/disassembler.py
chiasm_shell.egg-info/PKG-INFO
chiasm_shell.egg-info/SOURCES.txt
chiasm_shell.egg-info/dependency_links.txt
chiasm_shell.egg-info/entry_points.txt
chiasm_shell.egg-info/requires.txt
chiasm_shell.egg-info/top_level.txt
chiasm_shell.egg-info/zip-safe