Metadata-Version: 1.1
Name: chiasm-shell
Version: 1.0.0a8
Summary: CLI for assembly/disassembly powered by Keystone/Capstone.
Home-page: https://github.com/0xbc/chiasm-shell
Author: Ben Cheney
Author-email: ben.cheney@gmail.com
License: MIT
Download-URL: https://github.com/0xbc/chiasm-shell/tarball/1.0.0a8
Keywords: disassembler,assembler
Platform: UNKNOWN
Classifier: Development Status :: 3 - Alpha
Classifier: Environment :: Console
Classifier: Intended Audience :: Information Technology
Classifier: License :: OSI Approved :: MIT License
Classifier: Natural Language :: English
Classifier: Operating System :: OS Independent
Classifier: Programming Language :: Python
Classifier: Topic :: Security
Classifier: Topic :: Software Development :: Assemblers
Classifier: Topic :: Software Development :: Disassemblers
